{
  "source": "HouseSeats",
  "last_updated": "2026-02-27T21:56:39 PT",
  "last_successful_run": "2026-02-27T21:56:39 PT",
  "count": 7,
  "shows": [
    {
      "source": "HouseSeats",
      "name": "EIGHTIES THINGS: Stranger Things 80s Night",
      "link": "https://lv.houseseats.com/member/tickets/view/?showid=9183",
      "date": "February 28th",
      "image": "https://lv.houseseats.com/resources/media/9183.jpg",
      "rare": true
    },
    {
      "source": "HouseSeats",
      "name": "Guerrilla Radio - A Night of Musical Chaos",
      "link": "https://lv.houseseats.com/member/tickets/view/?showid=9184",
      "date": "February 28th",
      "image": "https://lv.houseseats.com/resources/media/9184.jpg",
      "rare": true
    },
    {
      "source": "HouseSeats",
      "name": "Y2K AF",
      "link": "https://lv.houseseats.com/member/tickets/view/?showid=8446",
      "date": "February 28th",
      "image": "https://lv.houseseats.com/resources/media/8446.jpg",
      "rare": false
    },
    {
      "source": "HouseSeats",
      "name": "Scene Stealers",
      "link": "https://lv.houseseats.com/member/tickets/view/?showid=9058",
      "date": "February 28th",
      "image": "https://lv.houseseats.com/resources/media/9058.jpg",
      "rare": false
    },
    {
      "source": "HouseSeats",
      "name": "Matt Donnelly - The Mind Noodler",
      "link": "https://lv.houseseats.com/member/tickets/view/?showid=9185",
      "date": "March 1st",
      "image": "https://lv.houseseats.com/resources/media/9185.jpg",
      "rare": true
    },
    {
      "source": "HouseSeats",
      "name": "Steve Falcon's Comedy Hypnosis Hour",
      "link": "https://lv.houseseats.com/member/tickets/view/?showid=9178",
      "date": "March 3rd",
      "image": "https://lv.houseseats.com/resources/media/9178.jpg",
      "rare": false
    },
    {
      "source": "HouseSeats",
      "name": "Ladies Night Comedy Show",
      "link": "https://lv.houseseats.com/member/tickets/view/?showid=9177",
      "date": "March 3rd",
      "image": "https://lv.houseseats.com/resources/media/9177.jpg",
      "rare": true
    }
  ]
}