{
  "source": "HouseSeats",
  "last_updated": "2026-07-12T08:34:27 PT",
  "last_successful_run": "2026-07-12T08:34:27 PT",
  "count": 6,
  "shows": [
    {
      "source": "HouseSeats",
      "name": "Nathan Burton Magic Show",
      "link": "https://lv.houseseats.com/member/tickets/view/?showid=9028",
      "date": "July 12th",
      "image": "https://lv.houseseats.com/resources/media/9028.jpg",
      "rare": false
    },
    {
      "source": "HouseSeats",
      "name": "The Conjurors Secret Wonders",
      "link": "https://lv.houseseats.com/member/tickets/view/?showid=9209",
      "date": "July 12th",
      "image": "https://lv.houseseats.com/resources/media/9209.jpg",
      "rare": false
    },
    {
      "source": "HouseSeats",
      "name": "ROUGE",
      "link": "https://lv.houseseats.com/member/tickets/view/?showid=7118",
      "date": "July 12th",
      "image": "https://lv.houseseats.com/resources/media/7118.jpg",
      "rare": false
    },
    {
      "source": "HouseSeats",
      "name": "Merle Norman Cosmetic Studio: Skin Assessment/Express Facial Service (Las Vegas)",
      "link": "https://lv.houseseats.com/member/tickets/view/?showid=9374",
      "date": "July 14th",
      "image": "https://lv.houseseats.com/resources/media/9374.jpg",
      "rare": false
    },
    {
      "source": "HouseSeats",
      "name": "Merle Norman Cosmetic Studio: Skin Assessment/Express Facial Service (Henderson)",
      "link": "https://lv.houseseats.com/member/tickets/view/?showid=9373",
      "date": "July 15th",
      "image": "https://lv.houseseats.com/resources/media/9373.jpg",
      "rare": false
    },
    {
      "source": "HouseSeats",
      "name": "Seth Robichaux: No Filter, All Glitter - A Vegas Cabaret Show",
      "link": "https://lv.houseseats.com/member/tickets/view/?showid=9342",
      "date": "July 15th",
      "image": "https://lv.houseseats.com/resources/media/9342.jpg",
      "rare": false
    }
  ]
}