{
  "source": "HouseSeats",
  "last_updated": "2026-07-22T07:34:32 PT",
  "last_successful_run": "2026-07-22T07:34:32 PT",
  "email_enabled": false,
  "count": 8,
  "shows": [
    {
      "source": "HouseSeats",
      "name": "Seth Robichaux: No Filter, All Glitter - A Vegas Cabaret Show",
      "link": "https://lv.houseseats.com/member/tickets/view/?showid=9342",
      "date": "July 22nd",
      "image": "https://lv.houseseats.com/resources/media/9342.jpg",
      "rare": false
    },
    {
      "source": "HouseSeats",
      "name": "ROUGE",
      "link": "https://lv.houseseats.com/member/tickets/view/?showid=7118",
      "date": "July 22nd",
      "image": "https://lv.houseseats.com/resources/media/7118.jpg",
      "rare": false
    },
    {
      "source": "HouseSeats",
      "name": "Merle Norman Cosmetic Studio: Skin Assessment/Express Facial Service (Henderson)",
      "link": "https://lv.houseseats.com/member/tickets/view/?showid=9373",
      "date": "July 23rd",
      "image": "https://lv.houseseats.com/resources/media/9373.jpg",
      "rare": false
    },
    {
      "source": "HouseSeats",
      "name": "Merle Norman Cosmetic Studio: Skin Assessment/Express Facial Service (Las Vegas)",
      "link": "https://lv.houseseats.com/member/tickets/view/?showid=9374",
      "date": "July 23rd",
      "image": "https://lv.houseseats.com/resources/media/9374.jpg",
      "rare": false
    },
    {
      "source": "HouseSeats",
      "name": "Von Clap Back Family Singers",
      "link": "https://lv.houseseats.com/member/tickets/view/?showid=9059",
      "date": "July 24th",
      "image": "https://lv.houseseats.com/resources/media/9059.jpg",
      "rare": false
    },
    {
      "source": "HouseSeats",
      "name": "Vegas' Dumbest Show about 'Murica",
      "link": "https://lv.houseseats.com/member/tickets/view/?showid=9253",
      "date": "July 25th",
      "image": "https://lv.houseseats.com/resources/media/9253.jpg",
      "rare": true
    },
    {
      "source": "HouseSeats",
      "name": "Scene Stealers",
      "link": "https://lv.houseseats.com/member/tickets/view/?showid=9058",
      "date": "July 25th",
      "image": "https://lv.houseseats.com/resources/media/9058.jpg",
      "rare": true
    },
    {
      "source": "HouseSeats",
      "name": "Louie TheSinger",
      "link": "https://lv.houseseats.com/member/tickets/view/?showid=9384",
      "date": "July 26th",
      "image": "https://lv.houseseats.com/resources/media/9384.jpg",
      "rare": true
    }
  ]
}