{
  "source": "HouseSeats",
  "last_updated": "2026-04-17T13:08:33 PT",
  "last_successful_run": "2026-04-17T13:08:33 PT",
  "count": 10,
  "shows": [
    {
      "source": "HouseSeats",
      "name": "ClueX",
      "link": "https://lv.houseseats.com/member/tickets/view/?showid=9226",
      "date": "April 17th",
      "image": "https://lv.houseseats.com/resources/media/9226.jpg",
      "rare": false
    },
    {
      "source": "HouseSeats",
      "name": "Wrestling Trivia Night",
      "link": "https://lv.houseseats.com/member/tickets/view/?showid=9230",
      "date": "April 17th",
      "image": "https://lv.houseseats.com/resources/media/9230.jpg",
      "rare": false
    },
    {
      "source": "HouseSeats",
      "name": "Billy Gardell",
      "link": "https://lv.houseseats.com/member/tickets/view/?showid=9255",
      "date": "April 17th",
      "image": "https://lv.houseseats.com/resources/media/9255.jpg",
      "rare": false
    },
    {
      "source": "HouseSeats",
      "name": "Zazu Comedy Nights",
      "link": "https://lv.houseseats.com/member/tickets/view/?showid=9256",
      "date": "April 17th",
      "image": "https://lv.houseseats.com/resources/media/9256.jpg",
      "rare": false
    },
    {
      "source": "HouseSeats",
      "name": "HIT USA RADIO",
      "link": "https://lv.houseseats.com/member/tickets/view/?showid=9232",
      "date": "April 17th",
      "image": "https://lv.houseseats.com/resources/media/9232.jpg",
      "rare": false
    },
    {
      "source": "HouseSeats",
      "name": "Whisky Mixer - Improv Party Night",
      "link": "https://lv.houseseats.com/member/tickets/view/?showid=9182",
      "date": "April 17th",
      "image": "https://lv.houseseats.com/resources/media/9182.jpg",
      "rare": false
    },
    {
      "source": "HouseSeats",
      "name": "WOW - The Vegas Spectacular",
      "link": "https://lv.houseseats.com/member/tickets/view/?showid=4878",
      "date": "April 18th",
      "image": "https://lv.houseseats.com/resources/media/4878.jpg",
      "rare": false
    },
    {
      "source": "HouseSeats",
      "name": "ROYAL THUNDER w/ Drowning Spree, Heroine Honey",
      "link": "https://lv.houseseats.com/member/tickets/view/?showid=9250",
      "date": "April 18th",
      "image": "https://lv.houseseats.com/resources/media/9250.jpg",
      "rare": false
    },
    {
      "source": "HouseSeats",
      "name": "Guess Who's High",
      "link": "https://lv.houseseats.com/member/tickets/view/?showid=8273",
      "date": "April 18th",
      "image": "https://lv.houseseats.com/resources/media/8273.jpg",
      "rare": false
    },
    {
      "source": "HouseSeats",
      "name": "ROCKLESQUE: SWEET TOOTH AND OTHER DELIGHTS",
      "link": "https://lv.houseseats.com/member/tickets/view/?showid=9252",
      "date": "April 19th",
      "image": "https://lv.houseseats.com/resources/media/9252.jpg",
      "rare": false
    }
  ]
}